murat_python_package/__init__.py
murat_python_package/__main__.py
murat_python_package/main_pkg/__init__.py
murat_python_package/main_pkg/main_module.py
murat_python_package/sub_pkg1/__init__.py
murat_python_package/sub_pkg1/sub_pkg1_pkg1/__init__.py
murat_python_package/sub_pkg1/sub_pkg1_pkg1/module1.py
murat_python_package/sub_pkg1/sub_pkg1_pkg1/module2.py
murat_python_package/sub_pkg1/sub_pkg1_pkg2/__init__.py
murat_python_package/sub_pkg1/sub_pkg1_pkg2/module3.py
murat_python_package/sub_pkg1/sub_pkg1_pkg2/module4.py
murat_python_package/sub_pkg2/__init__.py
murat_python_package/sub_pkg2/sub_pkg2_pkg1/__init__.py
murat_python_package/sub_pkg2/sub_pkg2_pkg1/module5.py
murat_python_package/sub_pkg2/sub_pkg2_pkg1/module6.py
murat_python_package/sub_pkg2/sub_pkg2_pkg2/__init__.py
murat_python_package/sub_pkg2/sub_pkg2_pkg2/module7.py
murat_python_package/sub_pkg2/sub_pkg2_pkg2/module8.py
murat_python_package-0.0.4.dist-info/AUTHORS
murat_python_package-0.0.4.dist-info/LICENSE
murat_python_package-0.0.4.dist-info/METADATA
murat_python_package-0.0.4.dist-info/WHEEL
murat_python_package-0.0.4.dist-info/entry_points.txt
murat_python_package-0.0.4.dist-info/top_level.txt
murat_python_package-0.0.4.dist-info/RECORD
