Metadata-Version: 2.1
Name: murat-python-package
Version: 0.0.4
Summary: A small example package
Home-page: https://github.com/muratcabuk/murat_python_package
Author: Murat Çabuk
Author-email: mcabuk@gmail.com
License: UNKNOWN
Project-URL: Bug Tracker, https://github.com/muratcabuk/murat_python_package/issues
Keywords: murat_python_package,web,test
Platform: UNKNOWN
Classifier: Programming Language :: Python :: 3
Classifier: License :: OSI Approved :: MIT License
Classifier: Operating System :: OS Independent
Requires-Python: >=3.6
Requires-Dist: click (>=8.0.0)
Requires-Dist: requests (>=2.0.0)
